{
  "anjanath": {
    "name": "Anjanath",
    "image": "https://cdn.discordapp.com/attachments/527913494595633152/527917556015693857/MHW-Anjanath_Icon.png",
    "size": "monster.size.large",
    "type": "monster.type.brute",
    "locations": [
      "location.forest",
      "location.desert"
    ],
    "weaknesses": [
      {
        "element": "element.water",
        "quantity": "3"
      },
      {
        "element": "element.thunder",
        "quantity": "2"
      },
      {
        "element": "element.ice",
        "quantity": "2"
      }
    ],
    "resistances": [
      "element.fire"
    ],
    "ailments": [
      "ailment.fireblight"
    ]
  }
}
